ezenc/__init__.py
ezenc/test.py
ezenc-0.1.1.dist-info/METADATA
ezenc-0.1.1.dist-info/WHEEL
ezenc-0.1.1.dist-info/top_level.txt
ezenc-0.1.1.dist-info/RECORD
