Metadata-Version: 2.1
Name: ezenc
Version: 0.1.1
Summary: A tool that can easily encrypt and decrypt. Utilizes the symmetric key cryptography method (AES).
Home-page: https://github.co.jp/
Author: bib_inf
Author-email: contact.bibinf@gmail.com
License: CC0 v1.0
Classifier: Programming Language :: Python :: 3
Classifier: Topic :: Software Development :: Libraries
Classifier: License :: CC0 1.0 Universal (CC0 1.0) Public Domain Dedication
Requires-Dist: ezpip
Requires-Dist: pycryptodome (>=3.21.0)
